pyqodeng-0.0.10-py3.11-nspkg.pth
pyqodeng/core/__init__.py
pyqodeng/core/cache.py
pyqodeng/core/icons.py
pyqodeng/core/share.py
pyqodeng/core/_designer_plugins/__init__.py
pyqodeng/core/_designer_plugins/code_edit_plugin.py
pyqodeng/core/_designer_plugins/errors_table_plugin.py
pyqodeng/core/_designer_plugins/interactive_console_plugin.py
pyqodeng/core/_designer_plugins/tab_widget_plugin.py
pyqodeng/core/_forms/__init__.py
pyqodeng/core/_forms/dlg_encodings_ui.py
pyqodeng/core/_forms/dlg_goto_line_ui.py
pyqodeng/core/_forms/dlg_preferred_encodings_editor_ui.py
pyqodeng/core/_forms/dlg_unsaved_files_ui.py
pyqodeng/core/_forms/pnl_encoding_ui.py
pyqodeng/core/_forms/pnl_read_only_ui.py
pyqodeng/core/_forms/popup_open_files_ui.py
pyqodeng/core/_forms/pyqode_core_rc.py
pyqodeng/core/_forms/search_panel_ui.py
pyqodeng/core/api/__init__.py
pyqodeng/core/api/client.py
pyqodeng/core/api/code_edit.py
pyqodeng/core/api/decoration.py
pyqodeng/core/api/encodings.py
pyqodeng/core/api/folding.py
pyqodeng/core/api/manager.py
pyqodeng/core/api/mode.py
pyqodeng/core/api/panel.py
pyqodeng/core/api/syntax_highlighter.py
pyqodeng/core/api/utils.py
pyqodeng/core/backend/__init__.py
pyqodeng/core/backend/server.py
pyqodeng/core/backend/workers.py
pyqodeng/core/dialogs/__init__.py
pyqodeng/core/dialogs/encodings.py
pyqodeng/core/dialogs/goto.py
pyqodeng/core/dialogs/unsaved_files.py
pyqodeng/core/managers/__init__.py
pyqodeng/core/managers/backend.py
pyqodeng/core/managers/decorations.py
pyqodeng/core/managers/file.py
pyqodeng/core/managers/modes.py
pyqodeng/core/managers/panels.py
pyqodeng/core/modes/__init__.py
pyqodeng/core/modes/autocomplete.py
pyqodeng/core/modes/autoindent.py
pyqodeng/core/modes/backspace.py
pyqodeng/core/modes/caret_line_highlight.py
pyqodeng/core/modes/case_converter.py
pyqodeng/core/modes/checker.py
pyqodeng/core/modes/code_completion.py
pyqodeng/core/modes/cursor_history.py
pyqodeng/core/modes/extended_selection.py
pyqodeng/core/modes/filewatcher.py
pyqodeng-0.0.10.dist-info/AUTHORS.rst
pyqodeng-0.0.10.dist-info/LICENSE
pyqodeng-0.0.10.dist-info/METADATA
pyqodeng-0.0.10.dist-info/WHEEL
pyqodeng-0.0.10.dist-info/entry_points.txt
pyqodeng-0.0.10.dist-info/namespace_packages.txt
pyqodeng-0.0.10.dist-info/top_level.txt
pyqodeng-0.0.10.dist-info/RECORD
